fastmodels/__init__.py
fastmodels/client.py
fastmodels/response_params.py
fastmodels/tests/__init__.py
fastmodels/tests/agent_completion_test.py
fastmodels/tests/agent_create_and_run_test.py
fastmodels/tests/agent_submit_tool_outputs_stream_test.py
fastmodels/tests/agent_submit_tool_outputs_test.py
fastmodels/tests/chat_completion_test.py
fastmodels/tests/code_review_test.py
fastmodels/tests/doc_parse_test.py
fastmodels/tests/doc_summarizer_test.py
fastmodels/tests/image_summarize_test.py
fastmodels/tests/meeting_minutes_test.py
fastmodels/tests/pota-anlyst_test.py
fastmodels/tests/speech_to_text_test.py
fastmodels_kit-0.1.8.dist-info/METADATA
fastmodels_kit-0.1.8.dist-info/WHEEL
fastmodels_kit-0.1.8.dist-info/top_level.txt
fastmodels_kit-0.1.8.dist-info/RECORD
